<?xml version="1.0"?>
<!--
Snap Websites Server == hashtag plugin database setup
Copyright (C) 2013-2017  Made to Order Software Corp.

This program is free software; you can redistribute it and/or modify
it under the terms of the GNU General Public License as published by
the Free Software Foundation; either version 2 of the License, or
(at your option) any later version.

This program is distributed in the hope that it will be useful,
but WITHOUT ANY WARRANTY; without even the implied warranty of
MERCHANTABILITY or FITNESS FOR A PARTICULAR PURPOSE.  See the
GNU General Public License for more details.

You should have received a copy of the GNU General Public License
along with this program; if not, write to the Free Software
Foundation, Inc., 51 Franklin St, Fifth Floor, Boston, MA  02110-1301  USA
-->
<snap-tree>
  <content path="/admin/settings/hashtag" owner="output">
    <param name="content::title" revision="revision">Hashtag Settings</param>
    <param name="content::body" revision="revision">
      <![CDATA[<p>Hashtag Settings.</p>]]>
    </param>
    <param name="permissions::dynamic" type="int8" revision="global">1</param>
    <param name="editor::layout" revision="global" overwrite="yes">"hashtag-settings-page";</param>
    <param name="layout::layout" revision="global" overwrite="yes">"hashtag-settings-parser";</param>
    <link name="content::page_type" to="content::page" mode="1:*">/types/taxonomy/system/content-types/page/private</link>
    <link name="permissions::direct::action::administer" to="permissions::link_back::administer" mode="*:*">/types/permissions/rights/administer/website/info</link>
  </content>
  <content path="/images/hashtag">
    <param name="content::title" revision="revision">Hashtag Images</param>
    <param name="content::body" revision="revision">
      <![CDATA[<p>Various images used by the hashtag plugin.</p>]]>
    </param>
    <link name="permissions::direct::action::view" to="permissions::link_back::view" mode="*:*">/types/permissions/rights/view/attachment/public</link>
    <link name="permissions::direct::action::administer" to="permissions::link_back::administer" mode="*:*">/types/permissions/rights/administer/website/info</link>
    <attachment name="hashtag-logo" type="attachment/public">
      <path>:/images/hashtag/hashtag-logo-64x64.png</path>
      <mime-type>image/png</mime-type>
    </attachment>
  </content>
  <content path="/types/taxonomy/system/content-types/hashtag" owner="output">
    <!-- this is only the default, you can always change the root tag for
         the hashtag; also you can define a specific hashtag on a per page
         type basis (i.e. blog hashtags, news hashtags, etc.) -->
    <param name="content::title" revision="revision">Hashtag Tags</param>
    <param name="content::body" revision="revision">
      <![CDATA[<p>List of Hashtag tags.</p>]]>
    </param>
    <link name="content::page_type" to="content::page" mode="1:*">/types/taxonomy/system/content-types/page/public</link>
    <!-- TODO: make this a list -->
  </content>
  <content path="/types/taxonomy/system/content-types/hashtag/test" owner="output">
    <param name="content::title" revision="revision">#test Hashtag!</param>
    <param name="content::body" revision="revision">
      <![CDATA[<p>A temporary #test, try to remove before checking in...</p>]]>
    </param>
    <link name="content::page_type" to="content::page" mode="1:*">/types/taxonomy/system/content-types/page/public</link>
    <!-- TODO: make this a list -->
  </content>
  <content path="/css/hashtag">
    <param name="content::title" revision="revision">Default CSS for Hashtag Links</param>
    <param name="content::body" revision="revision">
      <![CDATA[<p>The cascading style sheets for hashtag links generated by the hashtag plugin.</p>]]>
    </param>
    <link name="permissions::direct::action::administer" to="permissions::link_back::administer" mode="*:*">/types/permissions/rights/administer/website/info</link>
    <attachment name="hashtag" type="attachment/public">
      <path>qrc:/css/hashtag/hashtag.css</path>
      <mime-type>text/css</mime-type>
    </attachment>
  </content>
</snap-tree>
<!-- vim: ts=2 sw=2 et syntax=xml
-->
